shelved_cache/__init__.py
shelved_cache/decorators.py
shelved_cache/keys.py
shelved_cache/persistent_cache.py
shelved_cache-0.5.0.dist-info/METADATA
shelved_cache-0.5.0.dist-info/WHEEL
shelved_cache-0.5.0.dist-info/licenses/LICENSE
shelved_cache-0.5.0.dist-info/RECORD
