Metadata-Version: 2.4
Name: shelved_cache
Version: 0.5.0
Summary: Persistent cache for Python cachetools.
License: MIT
License-File: LICENSE
Author: Marius Helf
Author-email: helfsmarius@gmail.com
Requires-Python: >=3.10.0,<4.0.0
Classifier: Development Status :: 4 - Beta
Classifier: License :: OSI Approved :: MIT License
Classifier: Programming Language :: Python :: 3
Classifier: Programming Language :: Python :: 3.10
Classifier: Programming Language :: Python :: 3.11
Classifier: Programming Language :: Python :: 3.12
Classifier: Programming Language :: Python :: 3.13
Classifier: Programming Language :: Python :: 3.14
Classifier: Programming Language :: Python :: Implementation :: PyPy
Requires-Dist: cachetools (>=4.2.2,<7.0.0)
Project-URL: Documentation, https://github.com/mariushelf/shelved_cache
Project-URL: Homepage, https://github.com/mariushelf/shelved_cache
Project-URL: Repository, https://github.com/mariushelf/shelved_cache
